jmcomic_ai/__init__.py
jmcomic_ai/cli.py
jmcomic_ai/core.py
jmcomic_ai/mcp/__init__.py
jmcomic_ai/mcp/server.py
jmcomic_ai/skills/__init__.py
jmcomic_ai/skills/manager.py
jmcomic_ai/skills/jmcomic/SKILL.md
jmcomic_ai/skills/jmcomic/assets/option_schema.json
jmcomic_ai/skills/jmcomic/references/examples.md
jmcomic_ai/skills/jmcomic/references/reference.md
jmcomic_ai/skills/jmcomic/scripts/album_info.py
jmcomic_ai/skills/jmcomic/scripts/batch_download.py
jmcomic_ai/skills/jmcomic/scripts/doctor.py
jmcomic_ai/skills/jmcomic/scripts/download_covers.py
jmcomic_ai/skills/jmcomic/scripts/download_photo.py
jmcomic_ai/skills/jmcomic/scripts/ranking_tracker.py
jmcomic_ai/skills/jmcomic/scripts/search_export.py
jmcomic_ai/skills/jmcomic/scripts/validate_config.py
jmcomic_ai-0.0.2.dist-info/METADATA
jmcomic_ai-0.0.2.dist-info/WHEEL
jmcomic_ai-0.0.2.dist-info/entry_points.txt
jmcomic_ai-0.0.2.dist-info/licenses/LICENSE
jmcomic_ai-0.0.2.dist-info/RECORD
