Metadata-Version: 2.4
Name: jmcomic-ai
Version: 0.0.2
Summary: AI-powered JMComic crawler with MCP server and skills management for seamless AI agent integration
Project-URL: Homepage, https://github.com/hect0x7/jmcomic-ai
Project-URL: Repository, https://github.com/hect0x7/jmcomic-ai
Project-URL: Issues, https://github.com/hect0x7/jmcomic-ai/issues
Project-URL: Documentation, https://github.com/hect0x7/jmcomic-ai#readme
Author-email: hect0x7 <93357912+hect0x7@users.noreply.github.com>
License-Expression: MIT
License-File: LICENSE
Keywords: agent,ai,comic,crawler,jmcomic,manga,mcp
Classifier: Development Status :: 4 - Beta
Classifier: Environment :: Console
Classifier: Intended Audience :: Developers
Classifier: License :: OSI Approved :: MIT License
Classifier: Operating System :: OS Independent
Classifier: Programming Language :: Python :: 3
Classifier: Programming Language :: Python :: 3.10
Classifier: Programming Language :: Python :: 3.11
Classifier: Programming Language :: Python :: 3.12
Classifier: Programming Language :: Python :: 3.13
Classifier: Topic :: Internet :: WWW/HTTP :: Indexing/Search
Classifier: Topic :: Software Development :: Libraries :: Python Modules
Requires-Python: >=3.10
Requires-Dist: jmcomic>=2.6.11
Requires-Dist: mcp
Requires-Dist: typer
